graphletorbit.py
graphletorbit-0.0.1.dist-info/LICENSE
graphletorbit-0.0.1.dist-info/METADATA
graphletorbit-0.0.1.dist-info/WHEEL
graphletorbit-0.0.1.dist-info/top_level.txt
graphletorbit-0.0.1.dist-info/RECORD
